gaussdb/__init__.py
gaussdb/_acompat.py
gaussdb/_adapters_map.py
gaussdb/_capabilities.py
gaussdb/_cmodule.py
gaussdb/_column.py
gaussdb/_compat.py
gaussdb/_connection_base.py
gaussdb/_connection_info.py
gaussdb/_conninfo_attempts.py
gaussdb/_conninfo_attempts_async.py
gaussdb/_conninfo_utils.py
gaussdb/_copy.py
gaussdb/_copy_async.py
gaussdb/_copy_base.py
gaussdb/_cursor_base.py
gaussdb/_dns.py
gaussdb/_encodings.py
gaussdb/_enums.py
gaussdb/_oids.py
gaussdb/_pipeline.py
gaussdb/_preparing.py
gaussdb/_py_transformer.py
gaussdb/_queries.py
gaussdb/_struct.py
gaussdb/_tpc.py
gaussdb/_transformer.py
gaussdb/_typeinfo.py
gaussdb/_typemod.py
gaussdb/_tz.py
gaussdb/_wrappers.py
gaussdb/abc.py
gaussdb/adapt.py
gaussdb/client_cursor.py
gaussdb/connection.py
gaussdb/connection_async.py
gaussdb/conninfo.py
gaussdb/copy.py
gaussdb/cursor.py
gaussdb/cursor_async.py
gaussdb/dbapi20.py
gaussdb/errors.py
gaussdb/gaussdb_.py
gaussdb/generators.py
gaussdb/py.typed
gaussdb/raw_cursor.py
gaussdb/rows.py
gaussdb/server_cursor.py
gaussdb/sql.py
gaussdb/transaction.py
gaussdb/version.py
gaussdb/waiting.py
gaussdb/crdb/__init__.py
gaussdb/crdb/_types.py
gaussdb/crdb/connection.py
gaussdb/pq/__init__.py
gaussdb/pq/_debug.py
gaussdb/pq/_enums.py
gaussdb/pq/_pq_ctypes.py
gaussdb/pq/_pq_ctypes.pyi
gaussdb/pq/abc.py
gaussdb/pq/misc.py
gaussdb/pq/pq_ctypes.py
gaussdb/types/__init__.py
gaussdb/types/array.py
gaussdb/types/bool.py
gaussdb/types/composite.py
gaussdb/types/datetime.py
gaussdb/types/enum.py
gaussdb/types/hstore.py
gaussdb/types/json.py
gaussdb/types/multirange.py
gaussdb/types/net.py
gaussdb/types/none.py
gaussdb/types/numeric.py
gaussdb/types/numpy.py
gaussdb/types/range.py
gaussdb/types/shapely.py
gaussdb/types/string.py
gaussdb/types/uuid.py
gaussdb-1.0.4.dist-info/licenses/LICENSE.txt
gaussdb-1.0.4.dist-info/METADATA
gaussdb-1.0.4.dist-info/WHEEL
gaussdb-1.0.4.dist-info/top_level.txt
gaussdb-1.0.4.dist-info/RECORD
